sample/fourbitcounter.v
module cnt_bit(
    CK,
    RES,
    EN,
    Q,
    CU
);

    input   CK, RES, EN;
    output  Q, CU;
    reg     Q;

    always @(posedge CK or posedge RES) begin

        if (RES) begin
            Q <= 1'b0;
        end

        else if (EN) begin
            Q <= ~Q;
        end
        
    end

    assign CU = EN & Q;

endmodule // cnt_bit

module counter_hex(
    clk,
    res,
    q
);

    input clk, res;
    output [3:0] q;
    wire    [3:0] cu;
    cnt_bit cb0 (clk, res, 1'b1, q[0], cu[0]);
    cnt_bit cb1 (clk, res, cu[0], q[1], cu[1]);
    cnt_bit cb2 (clk, res, cu[1], q[2], cu[2]);
    cnt_bit cb3 (clk, res, cu[2], q[3], cu[3]);

endmodule // counter_hex

sample/fourbitcounter_test.v
`timescale 1ns/1ns

module top();

    reg clk, res;
    wire [3:0] q;

    parameter STEP = 100;
    always #(STEP/2) clk = ~clk;

    counter_hex counter_hex_i (clk, res, q);

    initial begin
        #0      res = 0; clk = 0;
        #STEP   res = 1;
        #STEP   res = 0;
        #(STEP*20) $finish();
    end

    initial begin
        $dumpfile("fourbitcounter.vcd");
        $dumpvars (0, top);
        $monitor ($stime, "res=%b clk=%b Q=%h", res, clk, q);
    end

    // initial begin
    //     #500 $finish();
    // end

endmodule

sample/fourbitcounter.vcd
$date
	Tue Dec 24 07:56:47 2019
$end
$version
	Icarus Verilog
$end
$timescale
	1ns
$end
$scope module top $end
$var wire 4 ! q [3:0] $end
$var reg 1 " clk $end
$var reg 1 # res $end
$scope module counter_hex_i $end
$var wire 1 " clk $end
$var wire 1 # res $end
$var wire 4 $ q [3:0] $end
$var wire 4 % cu [3:0] $end
$scope module cb0 $end
$var wire 1 " CK $end
$var wire 1 & CU $end
$var wire 1 ' EN $end
$var wire 1 # RES $end
$var reg 1 ( Q $end
$upscope $end
$scope module cb1 $end
$var wire 1 " CK $end
$var wire 1 ) CU $end
$var wire 1 * EN $end
$var wire 1 # RES $end
$var reg 1 + Q $end
$upscope $end
$scope module cb2 $end
$var wire 1 " CK $end
$var wire 1 , CU $end
$var wire 1 - EN $end
$var wire 1 # RES $end
$var reg 1 . Q $end
$upscope $end
$scope module cb3 $end
$var wire 1 " CK $end
$var wire 1 / CU $end
$var wire 1 0 EN $end
$var wire 1 # RES $end
$var reg 1 1 Q $end
$upscope $end
$upscope $end
$upscope $end
$enddefinitions $end
#0
$dumpvars
x1
x0
x/
x.
x-
x,
x+
x*
x)
x(
1'
x&
bx %
bx $
0#
0"
bx !
$end
#50
1"
#100
00
0-
0*
0/
0,
0)
b0 %
0&
01
0.
0+
b0 !
b0 $
0(
0"
1#
#150
1"
#200
0"
0#
#250
1*
b1 %
1&
b1 !
b1 $
1(
1"
#300
0"
#350
0*
0-
0&
b0 %
0)
0(
b10 !
b10 $
1+
1"
#400
0"
#450
1-
1)
1*
b11 %
1&
b11 !
b11 $
1(
1"
#500
0"
#550
0*
0-
00
0&
0)
b0 %
0,
0(
0+
b100 !
b100 $
1.
1"
#600
0"
#650
1*
b1 %
1&
b101 !
b101 $
1(
1"
#700
0"
#750
00
0,
0*
0-
0&
b0 %
0)
0(
b110 !
b110 $
1+
1"
#800
0"
#850
10
1,
1-
1)
1*
b111 %
1&
b111 !
b111 $
1(
1"
#900
0"
#950
0*
0-
00
0&
0)
0,
b0 %
0/
0(
0+
0.
b1000 !
b1000 $
11
1"
#1000
0"
#1050
1*
b1 %
1&
b1001 !
b1001 $
1(
1"
#1100
0"
#1150
0*
0-
0&
b0 %
0)
0(
b1010 !
b1010 $
1+
1"
#1200
0"
#1250
1-
1)
1*
b11 %
1&
b1011 !
b1011 $
1(
1"
#1300
0"
#1350
0/
0*
0-
00
0&
0)
b0 %
0,
0(
0+
b1100 !
b1100 $
1.
1"
#1400
0"
#1450
1*
b1 %
1&
b1101 !
b1101 $
1(
1"
#1500
0"
#1550
0/
00
0,
0*
0-
0&
b0 %
0)
0(
b1110 !
b1110 $
1+
1"
#1600
0"
#1650
1/
10
1,
1-
1)
1*
b1111 %
1&
b1111 !
b1111 $
1(
1"
#1700
0"
#1750
0*
0-
00
0&
0)
0,
b0 %
0/
0(
0+
0.
b0 !
b0 $
01
1"
#1800
0"
#1850
1*
b1 %
1&
b1 !
b1 $
1(
1"
#1900
0"
#1950
0*
0-
0&
b0 %
0)
0(
b10 !
b10 $
1+
1"
#2000
0"
#2050
1-
1)
1*
b11 %
1&
b11 !
b11 $
1(
1"
#2100
0"
#2150
0*
0-
00
0&
0)
b0 %
0,
0(
0+
b100 !
b100 $
1.
1"
