sample/fulladder.v
module fulladder(
    input x,
    input y,
    input cin,

    output A,
    output cout
);

    assign {cout, A} = cin + y + x;

endmodule // fulladder

sample/fulladder_test.v
`timescale 1ns/1ns

module fulladder_test();
    reg input1;
    reg input2;
    reg carryin;

    wire out;
    wire carryout;

    fulladder uut(
        .x(input1),
        .y(input2),
        .cin(carryin),
        .A(out),
        .cout(carryout)
    );

    initial begin
        input1 = 0;
        input2 = 0;
        carryin = 0;
    end

    // initial begin
    //     #20 input1 = 1;
    //     #20 input2 = 1;
    //     #20 input1 = 0;
    //     #20 carryin = 1;
    //     #20 input2 = 0;
    //     #20 input1 = 1;
    //     #20 input2 = 1;
    //     #40;
    // end

    initial begin
        forever begin
            #3 input1 = $random;
        end
    end

    initial begin
        forever begin
            #6 input2 = $random;
        end
    end

    initial begin
        forever begin
            #9 carryin = $random;
        end
    end

    initial begin
        #200 $finish();
    end

    initial begin
        $monitor("time=%2d, CIN=%1b, IN1=%1b, IN2=%1b, COUT=%1b, OUT=%1b", $time,carryin,input1,input2,carryout, out);
        $dumpfile("fulladder.vcd");
        $dumpvars(0, fulladder_test);
    end

endmodule

sample/fulladder.vcd
$date
	Sat Jan  4 11:59:37 2020
$end
$version
	Icarus Verilog
$end
$timescale
	1ns
$end
$scope module fulladder_test $end
$var wire 1 ! out $end
$var wire 1 " carryout $end
$var reg 1 # carryin $end
$var reg 1 $ input1 $end
$var reg 1 % input2 $end
$scope module uut $end
$var wire 1 # cin $end
$var wire 1 $ x $end
$var wire 1 % y $end
$var wire 1 " cout $end
$var wire 1 ! A $end
$upscope $end
$upscope $end
$enddefinitions $end
#0
$dumpvars
0%
0$
0#
0"
0!
$end
#6
1"
1$
1%
#9
1!
1#
#15
0!
0$
#21
1!
1$
#24
0!
0$
#33
1!
1$
#36
0!
0%
#39
1!
0"
0$
#48
1"
1$
1%
#54
0"
0$
0%
#60
0!
1"
1$
#63
1!
0"
0#
#66
0!
1"
1%
#72
0"
1!
0$
0%
1#
#75
0!
1"
1$
#78
1!
1%
#81
0"
0$
0#
#84
0!
0%
#90
1!
1#
#93
0!
1"
1$
#96
0$
1%
#99
1!
0"
0#
#102
0!
0%
#105
1!
1$
#108
1"
1%
1#
#114
0"
0$
0%
#117
0!
1"
1$
#120
0$
1%
#129
1!
1$
#132
0!
0$
#135
1!
1$
#138
0!
0$
#141
1!
1$
#144
0"
0$
0%
#150
0!
1"
1$
#153
1!
0"
0$
#156
0!
1"
1$
#162
1!
1%
#165
0!
0$
#168
1!
1$
#171
0!
0$
#174
1!
0"
0%
#180
0!
0#
#183
1!
1$
#186
0!
1"
1%
#189
1!
1#
#192
0!
0%
#198
1!
0"
0#
