sample/fulladder.v
module fulladder(
    input x,
    input y,
    input cin,

    output A,
    output cout
);

    assign {cout, A} = cin + y + x;
    // assign A = ((~cin) & x & (~y));
    // assign cout = ((~cin) & x & y);

endmodule // fulladder

sample/fulladder_test.v
`timescale 1ns/1ns

module fulladder_test();
    reg input1;
    reg input2;
    reg carryin;

    wire out;
    wire carryout;

    fulladder uut(
        .x(input1),
        .y(input2),
        .cin(carryin),
        .A(out),
        .cout(carryout)
    );

    initial begin
        input1 = 0;
        input2 = 0;
        carryin = 0;
    end

    initial begin
        #20 input1 = 1;
        #20 input2 = 1;
        #20 input1 = 0;
        #20 carryin = 1;
        #20 input2 = 0;
        #20 input1 = 1;
        #20 input2 = 1;
        #40;
    end

    // initial begin
    //     forever begin
    //         #3 input1 = $random;
    //     end
    // end

    // initial begin
    //     forever begin
    //         #6 input2 = $random;
    //     end
    // end

    // initial begin
    //     forever begin
    //         #9 carryin = $random;
    //     end
    // end

    initial begin
        #200 $finish();
    end

    initial begin
        $monitor("time=%2d, CIN=%1b, IN1=%1b, IN2=%1b, COUT=%1b, OUT=%1b", $time,carryin,input1,input2,carryout, out);
        $dumpfile("fulladder.vcd");
        $dumpvars(0, fulladder_test);
    end

endmodule

sample/fulladder.vcd
$date
	Thu Jan  9 21:37:08 2020
$end
$version
	Icarus Verilog
$end
$timescale
	1ns
$end
$scope module fulladder_test $end
$var wire 1 ! out $end
$var wire 1 " carryout $end
$var reg 1 # carryin $end
$var reg 1 $ input1 $end
$var reg 1 % input2 $end
$scope module uut $end
$var wire 1 # cin $end
$var wire 1 $ x $end
$var wire 1 % y $end
$var wire 1 " cout $end
$var wire 1 ! A $end
$upscope $end
$upscope $end
$enddefinitions $end
#0
$dumpvars
0%
0$
0#
0"
0!
$end
#20
1!
1$
#40
0!
1"
1%
#60
1!
0"
0$
#80
0!
1"
1#
#100
1!
0"
0%
#120
0!
1"
1$
#140
1!
1%
