sample/gatelevel.v
module gates (
    input a_input,
    input b_input,
    output c_and,
    output d_or,
    output e_xor
);

    and (c_and, a_input, b_input);  // c is the output, a and b are inputs
    or  (d_or, a_input, b_input);  // d is the output, a and b are inputs
    xor (e_xor, a_input, b_input);  // e is the output, a and b are inputs

endmodule

sample/gatelevel_test.v
module gatelevel();
    //input
    reg a;
    reg b;
    // output
    wire c;
    wire d;
    wire e;

    gates uut (
        .a_input(a),
        .b_input(b),
        .c_and(c),
        .d_or(d),
        .e_xor(e)        
    );

    integer i;

    initial begin
        a = 0;
        b = 0;
    end

    initial begin
        for (i=0; i<20; i=i+1) begin
            #1 a <= $random;
            b <= $random;
        end
    end

    initial begin
        // #200 $finish();
        $monitor("t=%0t, a=%0b, c=%0b, c(and)=%0b, d(or)=%0b, e(xor)=%0b \n", $time, a, b, c, d, e);
        $dumpfile("gatelevel.vcd");
        $dumpvars(0, gatelevel);
    end

endmodule // gate

sample/gatelevel.vcd
$date
	Wed Jan  1 11:01:14 2020
$end
$version
	Icarus Verilog
$end
$timescale
	1s
$end
$scope module gatelevel $end
$var wire 1 ! e $end
$var wire 1 " d $end
$var wire 1 # c $end
$var reg 1 $ a $end
$var reg 1 % b $end
$var integer 32 & i [31:0] $end
$scope module uut $end
$var wire 1 $ a_input $end
$var wire 1 % b_input $end
$var wire 1 # c_and $end
$var wire 1 " d_or $end
$var wire 1 ! e_xor $end
$upscope $end
$upscope $end
$enddefinitions $end
#0
$dumpvars
b0 &
0%
0$
0#
0"
0!
$end
#1
1"
1!
1%
b1 &
#2
1#
0!
1$
b10 &
#3
b11 &
#4
0#
1!
0%
b100 &
#5
1#
0!
1%
b101 &
#6
0#
1!
0$
b110 &
#7
0%
1$
b111 &
#8
b1000 &
#9
b1001 &
#10
1#
0!
1%
b1010 &
#11
0#
1!
0$
b1011 &
#12
0"
0!
0%
b1100 &
#13
1"
1!
1%
b1101 &
#14
b1110 &
#15
1#
0!
1$
b1111 &
#16
0#
1!
0%
b10000 &
#17
0"
0!
0$
b10001 &
#18
1"
1!
1%
b10010 &
#19
b10011 &
#20
1#
0!
1$
b10100 &
