sample/halfadder.v
module halfadder(
    input x,
    input y,
    output A,
    output cout
);

    assign cout = x & y;
    assign A = x ^ y;

endmodule // halfadder

sample/halfadder_test.v
`timescale 1ns/1ns

module halfadder_test();
    reg input1;
    reg input2;

    wire out;
    wire carryout;

    halfadder uut(
        .x(input1),
        .y(input2),
        .A(out),
        .cout(carryout)
    );

    initial begin
        input1 = 0;
        input2 = 0;
    end

    initial begin
        forever begin
            #5 input1 = $random;
        end
    end

    initial begin
        forever begin
            #5 input2 = $random;
        end
    end

    initial begin
        #100 $finish();
    end

    initial begin
        $monitor("time=%2d, IN1=%1b, IN2=%1b, CarryOut=%1b, OUT=%1b", $time, input1, input2, carryout, out);
        $dumpfile("halfadder.vcd");
        $dumpvars(0, halfadder_test);
    end

endmodule

sample/halfadder.vcd
$date
	Mon Jan  6 23:08:34 2020
$end
$version
	Icarus Verilog
$end
$timescale
	1ns
$end
$scope module halfadder_test $end
$var wire 1 ! out $end
$var wire 1 " carryout $end
$var reg 1 # input1 $end
$var reg 1 $ input2 $end
$scope module uut $end
$var wire 1 ! A $end
$var wire 1 " cout $end
$var wire 1 # x $end
$var wire 1 $ y $end
$upscope $end
$upscope $end
$enddefinitions $end
#0
$dumpvars
0$
0#
0"
0!
$end
#5
1!
1$
#10
1"
0!
1#
#20
0"
1!
0$
#25
1"
0!
1$
#30
0"
1!
0#
#35
0$
1#
#50
1"
0!
1$
#55
0"
1!
0#
#60
0!
0$
#65
1!
1$
#75
1"
0!
1#
#80
0"
1!
0$
#85
0!
0#
#90
1!
1$
