sample/ifstatement.v
module priory_encoder(
    input wire [3:0] x,
    output reg [2:0] pcode
);
    always @(x[3], x[2], x[1], x[0]) begin

        // if (x[4] == 1'b1) begin
        //     pcode = 3'b100;
        // end
        // else if (x[3] == 1'b1) begin
        //     pcode = 3'b011;
        // end
        // else if (x[2] == 1'b1) begin
        //     pcode = 3'b010;
        // end
        // else if (x[1] == 1'b1) begin
        //     pcode = 3'b001;
        // end
        // else begin
        //     pcode = 3'b000;
        // end
        
        if (x[3] == 1'b1) 
            pcode = 3'b100;
        else if (x[2] == 1'b1)
            pcode = 3'b011;
        else if (x[1] == 1'b1)
            pcode = 3'b010;
        else if (x[0] == 1'b1)
            pcode = 3'b001;
        else 
            pcode = 3'b000;
    end

endmodule

sample/ifstatement_test.v
module stimulus();
    reg [3:0] x;
    wire [2:0] pcode;

    // instantiate the unit under test (uut)
    priory_encoder uut(
        .x(x),
        .pcode(pcode)
    );

    initial begin
        // initialize inputs
        x = 4'b0000;

        #20 x = 4'b0001;
        #20 x = 4'b0010;
        #20 x = 4'b0011;
        #20 x = 4'b0100;
        #20 x = 4'b0101;
        #20 x = 4'b0110;
        #20 x = 4'b0111;
        #20 x = 4'b1000;
        #20 x = 4'b1001;
        #20 x = 4'b1010;
        #20 x = 4'b1011;
        #20 x = 4'b1100;
        #20 x = 4'b1101;
        #20 x = 4'b1110;
        #20 x = 4'b1111;
        #20 x = 4'b0000;

        #40 $finish();
    end

    initial begin
        $monitor("t=%3d, x=%4b, pcode=%3b", $time, x, pcode);
        $dumpfile("ifstatement.vcd");
        $dumpvars(0,stimulus);
    end
endmodule

sample/ifstatement.vcd
$date
	Thu Jan 16 22:50:27 2020
$end
$version
	Icarus Verilog
$end
$timescale
	1s
$end
$scope module stimulus $end
$var wire 3 ! pcode [2:0] $end
$var reg 4 " x [3:0] $end
$scope module uut $end
$var wire 4 # x [3:0] $end
$var reg 3 $ pcode [2:0] $end
$upscope $end
$upscope $end
$enddefinitions $end
#0
$dumpvars
b0 $
b0 #
b0 "
b0 !
$end
#20
b1 !
b1 $
b1 "
b1 #
#40
b10 !
b10 $
b10 "
b10 #
#60
b11 "
b11 #
#80
b11 !
b11 $
b100 "
b100 #
#100
b101 "
b101 #
#120
b110 "
b110 #
#140
b111 "
b111 #
#160
b100 !
b100 $
b1000 "
b1000 #
#180
b1001 "
b1001 #
#200
b1010 "
b1010 #
#220
b1011 "
b1011 #
#240
b1100 "
b1100 #
#260
b1101 "
b1101 #
#280
b1110 "
b1110 #
#300
b1111 "
b1111 #
#320
b0 !
b0 $
b0 "
b0 #
