sample/multiplexer.v
module multiplexer2_1(
    out,
    cntrl,
    in1,
    in2
);
    input cntrl, in1, in2;
    output out;
    assign out = cntrl ? in2 : in1;

endmodule

sample/multiplexer_test.v
module multiplexer2_tb();
    wire out;
    reg cntrl, in1, in2;

    multiplexer2_1 uut(out, cntrl, in1, in2);

    initial begin
        cntrl = 0;
        in1 = 0;
        in2 = 0;
    end

    initial begin
        #1;
        in1 = 1;
        in2 = 0;

        #1;
        in1 = 0;
        in2 = 1;

        #1;
        in1 = 1;
        in2 = 1;

        #1;
        in1 = 0;
        in2 = 0;

        #1;
        cntrl = 1;

        #1
        in1 = 1;
        in2 = 0;

        #1
        in1 = 0;
        in2 = 1;

        #1;
        in1 = 1;
        in2 = 1;

        #1;
        in1 = 0;
        in2 = 0;

        #1
        $finish();
    end

    initial begin
        $monitor($time, ", out=%b, cntrl=%b, in1=%b, in2=%b", out, cntrl, in1, in2);
        $dumpfile("multiplexer.vcd");
        $dumpvars(0, multiplexer2_tb);
    end

endmodule

sample/multiplexer.vcd
$date
	Mon Jan 13 12:44:55 2020
$end
$version
	Icarus Verilog
$end
$timescale
	1s
$end
$scope module multiplexer2_tb $end
$var wire 1 ! out $end
$var reg 1 " cntrl $end
$var reg 1 # in1 $end
$var reg 1 $ in2 $end
$scope module uut $end
$var wire 1 " cntrl $end
$var wire 1 # in1 $end
$var wire 1 $ in2 $end
$var wire 1 ! out $end
$upscope $end
$upscope $end
$enddefinitions $end
#0
$dumpvars
0$
0#
0"
0!
$end
#1
1!
1#
#2
0!
1$
0#
#3
1!
1#
#4
0!
0$
0#
#5
1"
#6
1#
#7
1!
1$
0#
#8
1#
#9
0!
0$
0#
