sample/test.v
module testtest(
    input a,
    input b,
    input c,
    input d,
    output outAandB,
    output outCandD,
    output result
);
    assign outAandB = a & b;
    assign outCandD = c & d;
    assign result = outAandB & outCandD;

endmodule

sample/test_test.v
module testtest_test();
    reg inputA;
    reg inputB;
    reg inputC;
    reg inputD;

    wire out;

    testtest uut(
        .a(inputA),
        .b(inputB),
        .c(inputC),
        .d(inputD),
        .result(out)
    );

    initial begin
        inputA = 0;
        inputB = 0;
        inputC = 0;
        inputD = 0;
    end

    initial begin
        #1;
        inputA = 1;
        inputB = 0;
        inputC = 0;
        inputD = 0;

        #1;
        inputA = 0;
        inputB = 1;
        inputC = 0;
        inputD = 0;

        #1;
        inputA = 1;
        inputB = 1;
        inputC = 0;
        inputD = 0;

        #1;
        inputA = 0;
        inputB = 0;
        inputC = 0;
        inputD = 0;

        #1;
        inputA = 0;
        inputB = 0;
        inputC = 1;
        inputD = 0;

        #1;
        inputA = 0;
        inputB = 0;
        inputC = 0;
        inputD = 1;

        #1;
        inputA = 0;
        inputB = 0;
        inputC = 1;
        inputD = 1;

        #1;
        inputA = 0;
        inputB = 0;
        inputC = 0;
        inputD = 0;

        #1;
        inputA = 1;
        inputB = 0;
        inputC = 1;
        inputD = 1;

        #1;
        inputA = 1;
        inputB = 1;
        inputC = 1;
        inputD = 0;

        #1;
        inputA = 0;
        inputB = 0;
        inputC = 0;
        inputD = 0;

        #1;
        inputA = 1;
        inputB = 1;
        inputC = 1;
        inputD = 1;

        #1;
        $finish();
    end

    initial begin
        $monitor("time=%0t, inputA=%0b, inputB=%0b, inputC=%0b, inputD=%0b, out=%0b \n", $time, inputA, inputB, inputC, inputD, out);
        $dumpfile("test.vcd");
        $dumpvars(0, testtest_test);
    end

endmodule

sample/test.vcd
$date
	Wed Jan 15 00:12:28 2020
$end
$version
	Icarus Verilog
$end
$timescale
	1s
$end
$scope module testtest_test $end
$var wire 1 ! out $end
$var reg 1 " inputA $end
$var reg 1 # inputB $end
$var reg 1 $ inputC $end
$var reg 1 % inputD $end
$scope module uut $end
$var wire 1 " a $end
$var wire 1 # b $end
$var wire 1 $ c $end
$var wire 1 % d $end
$var wire 1 & outAandB $end
$var wire 1 ' outCandD $end
$var wire 1 ! result $end
$upscope $end
$upscope $end
$enddefinitions $end
#0
$dumpvars
0'
0&
0%
0$
0#
0"
0!
$end
#1
1"
#2
1#
0"
#3
1&
1"
#4
0&
0#
0"
#5
1$
#6
1%
0$
#7
1'
1$
#8
0'
0%
0$
#9
1'
1%
1$
1"
#10
0'
1&
0%
1#
#11
0&
0$
0#
0"
#12
1!
1'
1&
1%
1$
1#
1"
